CHANGELOG.md
MANIFEST.in
README.md
setup.cfg
setup.py
versioneer.py
src/libreflow/__init__.py
src/libreflow.extensions.delete_anything.egg-info/PKG-INFO
src/libreflow.extensions.delete_anything.egg-info/SOURCES.txt
src/libreflow.extensions.delete_anything.egg-info/dependency_links.txt
src/libreflow.extensions.delete_anything.egg-info/top_level.txt
src/libreflow/extensions/__init__.py
src/libreflow/extensions/delete_anything/__init__.py
src/libreflow/extensions/delete_anything/_version.py